wearevenom/__init__.py
wearevenom/main.py
lappu_sa_venom-0.1.dist-info/METADATA
lappu_sa_venom-0.1.dist-info/WHEEL
lappu_sa_venom-0.1.dist-info/top_level.txt
lappu_sa_venom-0.1.dist-info/RECORD
