Metadata-Version: 2.1
Name: lappu-sa-venom
Version: 0.1
Requires-Dist: turtle
Requires-Dist: sketchpy
